retro_audit/__init__.py
retro_audit/main.py
retro_audit/prompts.py
retro_audit-2025.12.22084700.dist-info/METADATA
retro_audit-2025.12.22084700.dist-info/WHEEL
retro_audit-2025.12.22084700.dist-info/top_level.txt
retro_audit-2025.12.22084700.dist-info/RECORD
