Metadata-Version: 2.4
Name: retro-audit
Version: 2025.12.22084700
Summary: retro-audit helps gamers craft authentic, spam‑free retro content with structured feedback for better engagement.
Author-email: retro-audit <hi@eugene.plus>
License: MIT
Project-URL: Homepage, https://github.com/chigwell/retro-audit
Requires-Python: >=3.9
Requires-Dist: langchain-llm7>=0.0.0
Requires-Dist: llmatch-messages>=0.0.0
Requires-Dist: langchain-core>=0.3.0
